neuroimage_denoiser_gui/__init__.py
neuroimage_denoiser_gui/__main__.py
neuroimage_denoiser_gui/config.py
neuroimage_denoiser_gui/connector.py
neuroimage_denoiser_gui/icon.ico
neuroimage_denoiser_gui/icon.png
neuroimage_denoiser_gui/utils.py
neuroimage_denoiser_gui/window.py
neuroimage_denoiser_gui-1.4.4.dist-info/METADATA
neuroimage_denoiser_gui-1.4.4.dist-info/WHEEL
neuroimage_denoiser_gui-1.4.4.dist-info/licenses/LICENSE
neuroimage_denoiser_gui-1.4.4.dist-info/RECORD
