Metadata-Version: 2.4
Name: neuroimage_denoiser_gui
Version: 1.4.4
Summary: GUI Implementation for Neuorimage Denoiser (https://github.com/s-weissbach/neuroimage_denoiser)
Project-URL: Homepage, https://github.com/andreasmz/neuroimage_denoiser_gui
Project-URL: Repository, https://github.com/andreasmz/neuroimage_denoiser_gui
Project-URL: Issues, https://github.com/andreasmz/neuroimage_denoiser_gui/issues
Author: Andreas Brilka, Stephan Weißbach
License-Expression: MIT
License-File: LICENSE
Keywords: bioinformatics,denoising,neuroimage,python,torch
Classifier: Development Status :: 5 - Production/Stable
Classifier: Intended Audience :: Science/Research
Classifier: Programming Language :: Python :: 3
Classifier: Topic :: Scientific/Engineering :: Bio-Informatics
Classifier: Topic :: Scientific/Engineering :: Image Processing
Requires-Python: >=3.10
Requires-Dist: gpustat>=1.1.1
Requires-Dist: neuroimage-denoiser>=0.1.5
Requires-Dist: platformdirs>=4.3
Requires-Dist: psutil>=6.1
